krapplet/__init__.py
krapplet/__main__.py
krapplet/kr_backup.py
krapplet/kr_crypt.py
krapplet/kr_filepicker.py
krapplet/kr_json.py
krapplet/kr_memstorage.py
krapplet/kr_pass.py
krapplet/kr_password_entry.py
krapplet/kr_popup.py
krapplet/kr_secretstorage.py
krapplet/kr_storage.py
krapplet/kr_storage_select.py
krapplet/kr_test.py
krapplet/kr_time.py
krapplet/krapplet.py
krapplet-0.4.0.data/data/share/applications/krapplet.desktop
krapplet-0.4.0.data/data/share/icons/hicolor/48x48/apps/krapplet.png
krapplet-0.4.0.data/data/share/icons/hicolor/96x96/apps/krapplet.png
krapplet-0.4.0.dist-info/LICENSE
krapplet-0.4.0.dist-info/METADATA
krapplet-0.4.0.dist-info/WHEEL
krapplet-0.4.0.dist-info/entry_points.txt
krapplet-0.4.0.dist-info/top_level.txt
krapplet-0.4.0.dist-info/RECORD
