Metadata-Version: 2.1
Name: krapplet
Version: 0.4.0
Summary: A password manager written as a gnome-keyring applet
Home-page: https://gitlab.com/hfernh/krapplet
Author: Johannes Willem Fernhout
Author-email: hfern@fernhout.info
License: BSD 3-Clause License
Keywords: password manager,gnome-keyring,pass
Platform: Linux
Classifier: Development Status :: 4 - Beta
Classifier: License :: OSI Approved :: BSD License
Classifier: Operating System :: POSIX
Classifier: Programming Language :: Python
Classifier: Programming Language :: Python :: 3 :: Only
Classifier: Programming Language :: Python :: 3.10
Classifier: Programming Language :: Python :: 3.11
Classifier: Topic :: Security
Classifier: Topic :: Utilities
Requires-Python: >=3.10
License-File: LICENSE
Provides-Extra: gnomekeyring
Requires-Dist: secretstorage ; extra == 'gnomekeyring'
Provides-Extra: pass
Requires-Dist: python-gnupg ; extra == 'pass'
